{"pageInfo": {"page": 0, "numPages": 228, "pageSize": 1, "numEntries": 228}, "content": [{"matchId": "30796", "matchAltId": "13149e1a-6c8b-4b74-b4f6-a793fe96138a", "description": null, "eventPhase": null, "eventPhaseId": null, "venue": {"id": "831", "altId": "96fd67d7-ce0e-4213-9d77-ef1ce83517aa", "name": "Truman Bodden Stadium", "city": "Grand Cayman", "country": "Cayman Islands"}, "time": {"millis": 1670698800000, "gmtOffset": -5.0, "label": "2022-12-10"}, "attendance": null, "teams": [{"id": "707", "altId": "10625778-d3d8-448c-bd9a-ada76f5388c4", "name": "Cayman Islands", "abbreviation": "CAY", "countryCode": null, "annotations": null}, {"id": "1247", "altId": "b59358d8-28d0-4796-bef1-f1df6aef599a", "name": "Mexico", "abbreviation": "MEX", "countryCode": null, "annotations": null}], "scores": [35, 14], "kc": null, "status": "C", "clock": {"secs": 0, "label": "00:00"}, "outcome": "A", "events": [{"id": "2080", "altId": "037801d3-5055-4be4-ad77-6885f71c6029", "label": "Men's Internationals 2022", "sport": "mru", "start": {"millis": 1640995200000, "gmtOffset": 0.0, "label": "2022-01-01"}, "end": {"millis": 1672531199000, "gmtOffset": 0.0, "label": "2022-12-31"}, "abbr": null, "winningTeam": null, "eventStatus": {"eventStatusID": 6, "eventStatusName": "Finished"}, "seriesId": null, "seriesAltId": null, "rankingsWeight": 0.0, "impactPlayers": null, "teamPerformances": null}], "sport": "MRU", "competition": "Men's Internationals 2022", "weather": null, "rankingsWeight": null}]}